CHANGES.txt
LICENSE.txt
README.txt
bootstrap.py
buildout.cfg
setup.py
src/zope/__init__.py
src/zope.httpformdate.egg-info/PKG-INFO
src/zope.httpformdate.egg-info/SOURCES.txt
src/zope.httpformdate.egg-info/dependency_links.txt
src/zope.httpformdate.egg-info/namespace_packages.txt
src/zope.httpformdate.egg-info/not-zip-safe
src/zope.httpformdate.egg-info/requires.txt
src/zope.httpformdate.egg-info/top_level.txt
src/zope/httpformdate/README.txt
src/zope/httpformdate/__init__.py
src/zope/httpformdate/tests.py